mobly/controllers/cros/__init__.py
mobly/controllers/cros/cros_device.py
mobly/controllers/cros/cros_device_config.py
mobly/controllers/cros/data/testing_rsa
mobly/controllers/cros/examples/advanced_features_example_test.py
mobly/controllers/cros/examples/hello_world_test.py
mobly/controllers/cros/lib/__init__.py
mobly/controllers/cros/lib/autotest_helper.py
mobly/controllers/cros/lib/build_info.py
mobly/controllers/cros/lib/channel_file_streamer.py
mobly/controllers/cros/lib/constants.py
mobly/controllers/cros/lib/device_utils.py
mobly/controllers/cros/lib/file_clipper.py
mobly/controllers/cros/lib/notification_utils.py
mobly/controllers/cros/lib/ssh.py
mobly/controllers/cros/lib/tast_client.py
mobly/controllers/cros/lib/tast_service_manager.py
mobly/controllers/cros/lib/tast_service_wrapper.py
mobly/controllers/cros/lib/unix_utils.py
mobly/controllers/cros/lib/webdriver_manager.py
mobly/controllers/cros/lib/audio/__init__.py
mobly/controllers/cros/lib/audio/cras_control_utils.py
mobly/controllers/cros/lib/bluetooth/__init__.py
mobly/controllers/cros/lib/bluetooth/bluetooth_ui_utils.py
mobly/controllers/cros/lib/tast_services/__init__.py
mobly/controllers/cros/lib/tast_services/device_log_service.py
mobly/controllers/cros/lib/tast_services/floss_pandora_service.py
mobly/controllers/cros/lib/tast_services/screen_recorder_service.py
mobly/controllers/cros/lib/tast_services/tast_session_service.py
mobly/controllers/cros/lib/tast_services/test_fission_utils.py
mobly_cros-1.0.0.dist-info/licenses/LICENSE
tast/cros/services/cros/audio/__init__.py
tast/cros/services/cros/audio/cras_control_service_pb2.py
tast/cros/services/cros/audio/cras_control_service_pb2.pyi
tast/cros/services/cros/audio/cras_control_service_pb2_grpc.py
tast/cros/services/cros/audio/cras_test_service_pb2.py
tast/cros/services/cros/audio/cras_test_service_pb2.pyi
tast/cros/services/cros/audio/cras_test_service_pb2_grpc.py
tast/cros/services/cros/audio/cras_types_pb2.py
tast/cros/services/cros/audio/cras_types_pb2.pyi
mobly_cros-1.0.0.dist-info/METADATA
mobly_cros-1.0.0.dist-info/WHEEL
mobly_cros-1.0.0.dist-info/top_level.txt
mobly_cros-1.0.0.dist-info/RECORD
