Metadata-Version: 2.4
Name: mobly-cros
Version: 1.0.0
Summary: Mobly CrOS controller module for using Python code to operate CrOS devices in Mobly tests.
Home-page: https://github.com/google/mobly-cros
Author: Google Inc.
Author-email: minghaoli@google.com
Maintainer-email: Minghao Li <minghaoli@google.com>
License: 
Requires-Python: >=3.11
License-File: LICENSE
Requires-Dist: mobly>=1.12.2
Requires-Dist: paramiko>=2.10.4
Requires-Dist: pyzmq>=15.0.0
Requires-Dist: selenium==4.0.0
Requires-Dist: retry
Requires-Dist: dacite
Requires-Dist: grpcio
Requires-Dist: protobuf
Dynamic: author-email
Dynamic: home-page
Dynamic: license-file
Dynamic: requires-python
